{"id":"212f7f5a1e8081b28570d624ac2bc4d5","category":"몬스터","en":"Young Bronze Dragon","ko":"브론즈 드래곤 아성체","tag":"드래곤, 금속, CR 8","properties":{"url":"https://app.notion.com/p/212f7f5a1e8081b28570d624ac2bc4d5","도전지수":8,"보물":["도구"],"서식지":["해안"],"원문":"Young Bronze Dragon","이름":"브론즈 드래곤 아성체","종족":["드래곤","금속"],"크기":["대형"]},"content":"*대형 드래곤 (금속), 질서 선*\n---\n- **AC: **17 {color=\"red\"}\n- **HP:** 142 (15d10+60) {color=\"red\"}\n- **속도:** 40ft, 비행 80ft, 수영 40ft {color=\"red\"}\n- **선제권:** +3 (13) {color=\"red\"}\n---\n<table header-row=\"true\">\n<colgroup>\n<col width=\"52.333333333333336\">\n<col width=\"52.333333333333336\">\n<col width=\"52.333333333333336\">\n<col width=\"52.333333333333336\">\n<col width=\"52.333333333333336\">\n<col width=\"52.333333333333336\">\n</colgroup>\n<tr>\n<td>**근력**</td>\n<td>**민첩**</td>\n<td>**건강**</td>\n<td>**지능**</td>\n<td>**지혜**</td>\n<td>**매력**</td>\n</tr>\n<tr color=\"yellow_bg\">\n<td>21</td>\n<td>10</td>\n<td>19</td>\n<td>14</td>\n<td>13</td>\n<td>18</td>\n</tr>\n<tr color=\"purple_bg\">\n<td>+5</td>\n<td>+0</td>\n<td>+4</td>\n<td>+2</td>\n<td>+1</td>\n<td>+3</td>\n</tr>\n<tr color=\"purple_bg\">\n<td>+5</td>\n<td>+3</td>\n<td>+4</td>\n<td>+2</td>\n<td>+4</td>\n<td>+3</td>\n</tr>\n</table>\n---\n- **기술: **<span color=\"green\">[통찰](/1def7f5a1e808148a82bc030e637e4ec?pvs=25)</span> +4,** **<span color=\"green\">[포착](/165a87ea43778156b2c7dc395f3f26d6?pvs=25)</span> +7, <span color=\"green\">[은신](/1def7f5a1e808148a82bc030e637e4ec?pvs=25)</span> +3 {color=\"red\"}\n- **면역:** 번개 {color=\"red\"}\n- **감각:** <span color=\"green\">[맹시야](/1def7f5a1e80811281b4d71f9b44ff2e?pvs=25)</span> 30ft, <span color=\"green\">[암시야](/1def7f5a1e8081e9ae2ad6d4a70fa827?pvs=25)</span> 120ft, 상시 포착 17 {color=\"red\"}\n- **언어:** 공용어, 용언 {color=\"red\"}\n- **CR:** 8 (XP 3900, PB +3) {color=\"red\"}\n---\n### 특성 {color=\"yellow_bg\"}\n- **수륙양용: **공기와 수중 양쪽에서 호흡할 수 있습니다. {color=\"red\"}\n### 행동 {color=\"yellow_bg\"}\n- **다중공격:** 분쇄 공격을 세 번 가합니다. 이 중 한 개의 공격을 대신하여 반발 숨결을 사용할 수 있습니다. {color=\"red\"}\n- **분쇄:** <span color=\"gray\">*근거리 명중 굴림:*</span> +8, 간격 10ft. <span color=\"gray\">*명중:*</span> 16(2d10+5) 참격 피해. {color=\"red\"}\n- **번개 숨결 (재충전 5-6):** <span color=\"gray\">*민첩 내성 굴림:*</span> DC 15, 길이 60ft, 너비 5ft 직선의 모든 크리처. <span color=\"gray\">*실패:*</span> 49(9d10) 번개 피해. <span color=\"gray\">*성공:*</span>* *절반의 피해. {color=\"red\"}\n- **반발 숨결:** <span color=\"gray\">*근력 내성 굴림:*</span> DC 15, 30ft <span color=\"yellow\">[원뿔](/1def7f5a1e808149825ddd4af89ded1d?pvs=25)</span> 범위 안의 크리처. <span color=\"gray\">*실패: *</span>대상은 드래곤으로부터 직선으로 40ft까지 밀려나며, <span color=\"green\">[넘어짐](/1def7f5a1e80819d813ef3202e979b4d?pvs=25)</span> 상태가 됩니다. {color=\"red\"}\n---\n# 설명 {color=\"red_bg\"}\n브론즈 드래곤 아성체들은 각자 해적 퇴치나 폭풍으로부터의 공동체 보호와 같은 특정 분야의 전문가가 됩니다. 이들은 다양한 전문성을 지닌 동료들을 모아 신뢰할 수 있는 전문가 인맥을 구축합니다.\n## 브론즈 드래곤 {color=\"orange_bg\"}\n브론즈 드래곤이 머무는 곳에는 경이로움이 꽃피웁니다. 이 상상력 넘치고 신중한 금속룡은 위대함을 추구하며, 다른 이들이 잠재력을 실현하도록 돕습니다. 이들은 과거 문명의 유산과 새로운 발견을 보존하고 널리 공유하는 데 힘씁니다. 수명이 짧은 존재들과는 대화와 관계 형성을 통해 소통하지만, 누군가 타인의 성장 가능성을 방해한다면 전투도 마다하지 않습니다.\n브론즈 드래곤은 바다의 힘과 무한한 가능성을 사랑하며, 자연의 아름다움이 깃든 곳이나 보호하고 싶은 공동체 근처에 은신처를 만듭니다. 이들의 거처에는 언젠가 쓸모가 있으리라 믿는 보물들이 가득하며, 바다에 잃어버린 보물이나 침몰한 배의 재산을 찾아내 수집하는 것을 즐깁니다.\n---\n![](https://prod-files-secure.s3.us-west-2.amazonaws.com/8dffc202-0f6e-4adf-b208-fc378f0d8bf3/ffaa143c-ad8e-40a6-b3b7-cae1818a5205/638741964861113471.png)\n"}