{"id":"30af7f5a1e8080a5b5ddfd2c6a910410","category":"재주","en":"Chef","ko":"요리사","tag":null,"properties":{"url":"https://app.notion.com/p/30af7f5a1e8080a5b5ddfd2c6a910410","요구사항":"*4레벨 이상*","원문":"Chef","유형":["범용"],"이름":"요리사","출처":["PHB"]},"content":"<synced_block_reference url=\"https://app.notion.com/p/30af7f5a1e8080a5b5ddfd2c6a910410#30af7f5a1e80808f916df077d3bd0918\">\n\t*범용 재주 (4레벨 이상)* {color=\"gray\"}\n\t---\n\t다음과 같은 혜택을 얻습니다.\n\t<span color=\"red\">***능력 향상.***</span><span color=\"red\">* *</span>건강 또는 지혜 능력치를 1만큼 증가시킵니다(최대 20). {color=\"red\"}\n\t<span color=\"red\">***요리 도구.***</span>** **요리 도구 숙련을 얻습니다(이미 숙련이 없는 경우). {color=\"red\"}\n\t<span color=\"red\">***재충전 식사. ***</span>짧은 휴식<span color=\"red\">*** ***</span>중에 재료와 요리 도구를 사용하여 특별한 음식을 만들 수 있습니다. 이 음식은 당신의 숙련 보너스에 4를 더한 수만큼의 크리처가 먹을 수 있습니다. 짧은 휴식이 끝날 때, 이 음식을 먹고 히트 다이스를 하나 이상 소비하여 HP를 회복하는 크리처는 추가로 1d8 HP를 회복합니다. {color=\"red\"}\n\t<span color=\"red\">***강화 간식.***</span> 1시간의 작업이나 긴 휴식 동안 재료와 요리 도구를 사용하여 당신의 숙련 보너스만큼의 간식을 만들 수 있습니다. 이 특별한 간식은 제작 후 8시간 동안 유지됩니다. 크리처는 보조 행동으로 간식 하나를 먹어 당신의 숙련 보너스만큼의 임시 HP를 얻을 수 있습니다. {color=\"red\"}\n</synced_block_reference>"}