{"id":"1def7f5a1e80813db83ecb1b680895a2","category":"마법 아이템","en":"Wand of Paralysis","ko":"마비의 마법봉","tag":"희귀","properties":{"url":"https://app.notion.com/p/1def7f5a1e80813db83ecb1b680895a2","등급":["희귀"],"원문":"Wand of Paralysis","유형":["마법봉"],"이름":"마비의 마법봉","조율":"__YES__","참조":["PHB"]},"content":"*마법봉, 희귀 (주문시전자의 조율 필요)*\n---\n이 마법봉은 7개의 충전을 가지고 있습니다. 마법봉을 들고 있는 동안, <span color=\"green\">[마법](/1def7f5a1e8081d69aa0f579a00ee48b?pvs=25)</span> 행동을 사용해 1개의 충전을 소모하면 마법봉 끝에서 가느다란 푸른 광선을 발사할 수 있습니다. 이 광선은 60ft 내에서 볼 수 있는 크리처 하나를 목표로 날아갑니다. 대상은 DC 15 건강 내성 굴림을 해야 하며, 실패 시 1분 동안 <span color=\"green\">[마비](/1def7f5a1e80813daa06def1979cc255?pvs=25)</span> 상태가 됩니다. 대상은 대상의 턴이 끝날 때마다 내성 굴림을 다시 할 수 있으며, 성공 시 효과가 즉시 종료됩니다.\n- **충전 회복:** 이 마법봉은 매일 새벽에 1d6+1개의 소모된 충전을 회복합니다. 마지막 충전을 사용했다면 d20을 굴려야 하며, 1이 나올 경우 마법봉은 재가 되어 파괴됩니다. {color=\"red\"}\n---\n![](https://prod-files-secure.s3.us-west-2.amazonaws.com/8dffc202-0f6e-4adf-b208-fc378f0d8bf3/456857dc-b7a4-4fff-87b4-c275d8e00d35/638657414206989020.png)"}