{"id":"1f0f7f5a1e8080c19685c80c268ec442","category":"마법 아이템","en":"Tentacle Rod","ko":"촉수 막대","tag":"희귀","properties":{"url":"https://app.notion.com/p/1f0f7f5a1e8080c19685c80c268ec442","등급":["희귀"],"원문":"Tentacle Rod","유형":["막대"],"이름":"촉수 막대","조율":"__YES__","참조":["PHB"]},"content":"*막대, 희귀 (조율 필요)*\n---\n이 막대의 끝에는 세 개의 탄력적인 촉수가 달려 있습니다. 이 막대를 들고 있을 때, <span color=\"green\">[마법](/1def7f5a1e8081d69aa0f579a00ee48b?pvs=25)</span> 행동을 사용하여 촉수들을 뻗어 15ft 내에서 볼 수 있는 크리처들을 공격할 수 있습니다. 각 촉수는 +9 명중 보너스로 근거리 명중 굴림을 수행하며, 명중 시 1d6 정신 피해를 입힙니다. 한 대상에게 세 촉수가 모두 명중했다면, 대상은 DC 15의 민첩 내성 굴림을 해야 합니다. 실패 시 당신이 <span color=\"green\">[행동불능](/1def7f5a1e80816298c8fa0c11a20c2e?pvs=25)</span> 상태가 되거나, <span color=\"green\">[보조 행동](/1def7f5a1e808184bd10fe1afe311e2c?pvs=25)</span>으로 대상을 풀어주거나, 대상이 당신으로부터 15ft 이상 떨어질 때까지 <span color=\"green\">[포박](/1def7f5a1e80811fb651e78a8beed424?pvs=25)</span> 상태가 됩니다. 포박된 대상의 턴이 시작될 때마다 3d6 정신 피해를 받습니다. 대상의 턴이 끝날 때마다 내성 굴림을 다시 시도할 수 있으며, 성공하면 효과가 즉시 종료됩니다.\n---\n![](https://prod-files-secure.s3.us-west-2.amazonaws.com/8dffc202-0f6e-4adf-b208-fc378f0d8bf3/659e82b7-fc83-4c2d-8b3d-080e1091d8ac/638657414174306801.png)"}