{"id":"1f2f7f5a1e8080b58c7fd9e1a91eaf7f","category":"캐릭터 클래스","en":"Warrior of Shadow","ko":"그림자의 전사","tag":"Subclass","properties":{"url":"https://app.notion.com/p/1f2f7f5a1e8080b58c7fd9e1a91eaf7f","미리보기":["file://%7B%22source%22%3A%22https%3A%2F%2Fprod-files-secure.s3.us-west-2.amazonaws.com%2F0d976d7d-e60c-4eb7-b728-3fa22e24d31b%2F718eaeb2-0856-4d72-91bd-8cd919c17be8%2F%25EA%25B7%25B8%25EB%25A6%25BC%25EC%259E%2590.png%22%2C%22permissionRecord%22%3A%7B%22table%22%3A%22block%22%2C%22id%22%3A%221f2f7f5a-1e80-80b5-8c7f-d9e1a91eaf7f%22%2C%22spaceId%22%3A%228dffc202-0f6e-4adf-b208-fc378f0d8bf3%22%7D%7D"],"원문":"Warrior of Shadow","이름":"그림자의 전사","출처":["PHB"]},"content":"<synced_block_reference url=\"https://app.notion.com/p/1f2f7f5a1e8080b58c7fd9e1a91eaf7f#309f7f5a1e808070872be31925d0bfbe\">\n\t그림자의 전사들은 은신과 잠행의 기술을 연마하며 그림자의 세계인 섀도펠의 힘을 자유자재로 다룹니다. 그들은 어둠 속에서 자연스러운 편안함을 느끼며, 자신을 어둠으로 감싸 숨거나 그림자에서 그림자로 순간이동하며 망령같은 형태로 변신할 수 있습니다.\n\t## 3레벨: 그림자 무술 {color=\"yellow_bg\"}\n\t섀도펠의 힘을 다뤄 다음의 혜택을 얻습니다.\n\t<span color=\"red\">***암흑.***</span><span color=\"red\">* *</span>기력 1점을 소모하여 <span color=\"purple\">[*어둠*](/212f7f5a1e808107a173fcc5e0b44aef?pvs=25)</span> 주문을 구성요소 없이 시전할 수 있습니다. 이 특성으로 주문을 시전하면 주문의 영역 안을 볼 수 있으며, 주문이 지속되는 동안 당신의 턴 시작 시 주문의 <span color=\"yellow\">[어둠](/212f7f5a1e808106923cf450f1195125?pvs=25)</span>을 당신으로부터 60ft 이내의 다른 공간으로 이동시킬 수 있습니다. {color=\"red\"}\n\t<span color=\"red\">***암시야.***</span> 60ft 범위의 <span color=\"green\">[암시야](/212f7f5a1e8081c2b8bfc4f3225cb597?pvs=25)</span>를 얻습니다. 이미 암시야가 있다면 그 범위가 60ft 증가합니다. {color=\"red\"}\n\t<span color=\"red\">***그림자 환영.***</span> <span color=\"purple\">[*하급 환영*](/212f7f5a1e8081a29dd3f6da0776798e?pvs=25)</span>* *주문을 배웁니다. 주문시전 능력치는 지혜입니다. {color=\"red\"}\n\t## 6레벨: 그림자 걸음 {color=\"yellow_bg\"}\n\t<span color=\"yellow\">[약한 빛](/212f7f5a1e80816b935dfcf84e45fa93?pvs=25)</span> 또는 <span color=\"yellow\">[어둠](/212f7f5a1e808106923cf450f1195125?pvs=25)</span> 속에 있을 때, 보조 행동으로 60ft 이내의 약한 빛이나 어둠 속에 있는 비점유 공간으로 순간이동할 수 있습니다. 이후 현재 턴이 끝나기 전 첫 번째 근거리 공격에 유리 보정을 얻습니다.\n\t## **11레벨: 향상된 그림자 걸음** {color=\"yellow_bg\"}\n\t섀도펠과의 연결을 더욱 강화하여 순간이동 능력을 향상시킵니다. 그림자 걸음 사용 시 기력 1점을 소모하면 해당 턴에서 <span color=\"yellow\">[약한 빛](/212f7f5a1e80816b935dfcf84e45fa93?pvs=25)</span><span color=\"yellow\"> </span>또는 <span color=\"yellow\">[어둠](/212f7f5a1e808106923cf450f1195125?pvs=25)</span> 속에서 시작하고 끝내야 하는 제약을 무시할 수 있습니다. 또한 보조 행동의 일부로, 순간이동 직후 비무장 공격을 가할 수 있습니다.\n\t## **17레벨: 그림자 망토** {color=\"yellow_bg\"}\n\t<span color=\"yellow\">[약한 빛](/212f7f5a1e80816b935dfcf84e45fa93?pvs=25)</span> 또는 <span color=\"yellow\">[어둠](/212f7f5a1e808106923cf450f1195125?pvs=25)</span> 속에서 <span color=\"green\">[마법](/212f7f5a1e80818c96ccf2947fff33e7?pvs=25)</span> 행동으로 기력 3점을 소모하여 그림자로 자신을 감쌀 수 있습니다. 이 상태는 1분간 지속되며, <span color=\"green\">[행동불능](/212f7f5a1e8081aa8c00f5f8ac0b511c?pvs=25)</span> 상태가 되거나 <span color=\"yellow\">[밝은 빛](/212f7f5a1e8081239224f09b56e36bb4?pvs=25)</span> 속에서 턴을 마칠 때 종료됩니다. 이 상태에서 다음의 이점을 얻습니다.\n\t<span color=\"red\">***투명화.***</span> <span color=\"green\">[투명](/212f7f5a1e808181889cccb51c28dcff?pvs=25)</span> 상태가 됩니다. {color=\"red\"}\n\t<span color=\"red\">***부분적 비물질화.***</span> 점유된 공간을 <span color=\"yellow\">[험지](/212f7f5a1e808192b933e957c7d6ce16?pvs=25)</span>로 간주하여 통과할 수 있습니다. 만약 이러한 공간에서 턴을 종료하면, 이전에 있던 비점유 공간으로 되돌아갑니다. {color=\"red\"}\n\t<span color=\"red\">***그림자 연격. ***</span>기력 소모 없이 일진광풍을 사용할 수 있습니다. {color=\"red\"}\n</synced_block_reference>"}