{"id":"304f7f5a1e80803cbdcbfdee1ea9799a","category":"주문","en":"Thunderwave","ko":"천둥파","tag":"방출학파, 1레벨","properties":{"title":""},"content":"*방출술 1레벨*\n---\n**시전시간:** 1 행동\n**사거리/범위:** 자신/15ft 입방체\n**구성요소:** 음성, 동작\n**지속시간:** 즉시\n---\n당신은 강력한 천둥 에너지를 방출합니다. 당신을 원점으로 15ft <span color=\"yellow\">[입방체](/212f7f5a1e8081c4aedaf3d1fddf8ef7?pvs=25)</span> 범위의 크리처는 건강 <span color=\"yellow\">[내성 굴림](/212f7f5a1e8081e7b602d475b0605237?pvs=25)</span>을 해야 하며, 실패 시 2d8 천둥 피해를 받고, 10ft 밀쳐집니다. 성공 시에도 여전히 절반의 피해를 받습니다.\n추가로, 입방체 안에 있는 고정되지 않은 물체는 10ft 밀쳐지며, 이 주문의 천둥 소리는 최대 300ft 떨어진 곳까지 들릴 수 있습니다.\n**고등 시전:** 추가 주문 레벨마다 피해가 1d8씩 증가합니다.\n---\n**클래스:** 바드, 드루이드, 소서러, 위저드"}