{"id":"305f7f5a1e8080d4be0bed543c967f75","category":"주문","en":"Tree Stride","ko":"나무 활보","tag":"조형학파, 5레벨","properties":{"title":""},"content":"*창조술 5레벨*\n---\n**시전시간:** 1 행동\n**사거리/범위: **자신\n**구성요소:** 음성, 동작\n**지속시간:** 집중, 최대 1분까지\n---\n당신은 나무 안으로 들어가 같은 종류의 다른 나무로 이동할 수 있는 능력을 얻습니다. 두 나무는 모두 살아있어야 하며, 당신 이상의 체격이어야 합니다. 나무에 들어가려면 5ft의 속도를 사용해야 합니다. 나무에 들어가면 500ft 내에 있는 같은 종류의 나무들의 위치를 즉시 알 수 있으며, 나무에 들어가는 이동의 일환으로 그 나무들 중 하나로 이동하거나 현재 있는 나무에서 나올 수 있습니다. 목적지 나무의 5ft 내의 원하는 위치에 나타나려면 5ft의 속도를 추가로 사용해야 합니다. 속도가 남아있지 않다면 들어갔던 나무의 5ft 내에서 나타납니다.\n이 이동 능력은 턴당 한 번만 사용할 수 있으며, 반드시 나무 밖에서 턴을 끝내야 합니다.\n---\n**클래스:** 드루이드, 레인저\n"}