{"id":"212f7f5a1e808131877ac2effe3c0f08","category":"장비","en":"Iron Pot","ko":"철 냄비","tag":null,"properties":{"url":"https://app.notion.com/p/212f7f5a1e808131877ac2effe3c0f08","가치":2,"무게":10,"원문":"Iron Pot","유형":["모험 도구"],"이름":"철 냄비","출처":["SRD","PHB"]},"content":"<synced_block_reference url=\"https://app.notion.com/p/212f7f5a1e808131877ac2effe3c0f08#30bf7f5a1e808028b736f18fffe5fd9a\">\n\t*모험 도구, 일반* {color=\"gray\"}\n\t---\n\t<span color=\"red\">**무게:**</span> 10 lbs\n\t<span color=\"red\">**가치:**</span> 2 GP\n\t---\n\t철 냄비는 최대 1갤런의 용량을 담을 수 있습니다.\n</synced_block_reference>"}