{"id":"212f7f5a1e8081dfa9ecee2ad111fc77","category":"장비","en":"Mason's Tools","ko":"석공의 도구","tag":null,"properties":{"url":"https://app.notion.com/p/212f7f5a1e8081dfa9ecee2ad111fc77","가치":10,"무게":8,"원문":"Mason's Tools","유형":["도구"],"이름":"석공의 도구","출처":["SRD","PHB"]},"content":"<synced_block_reference url=\"https://app.notion.com/p/212f7f5a1e8081dfa9ecee2ad111fc77#30bf7f5a1e80802ba387eb453f9c2ddb\">\n\t*도구, 일반* {color=\"gray\"}\n\t---\n\t<span color=\"red\">**무게:**</span><span color=\"red\"> </span>8 lbs\n\t<span color=\"red\">**가치:**</span> 10 GP\n\t---\n\t<span color=\"red\">**능력:**</span><span color=\"red\"> </span>근력 {color=\"red\"}\n\t<span color=\"red\">**활용:**</span><span color=\"red\"> </span>돌에 기호나 구멍 새기기 (DC 10) {color=\"red\"}\n\t<span color=\"red\">**제작:**</span> <span color=\"brown\">[도르래와 걸쇠](/212f7f5a1e80813eb88fe219af5f56ca?pvs=25)</span> {color=\"red\"}\n</synced_block_reference>"}