{"id":"212f7f5a1e8081b68747cc7dd4de95ae","category":"장비","en":"Torch","ko":"횃불","tag":null,"properties":{"url":"https://app.notion.com/p/212f7f5a1e8081b68747cc7dd4de95ae","가치":0.01,"무게":1,"원문":"Torch","유형":["모험 도구"],"이름":"횃불","출처":["SRD","PHB"]},"content":"<synced_block_reference url=\"https://app.notion.com/p/212f7f5a1e8081b68747cc7dd4de95ae#30bf7f5a1e80800885fce0029c70414e\">\n\t*모험 도구, 일반* {color=\"gray\"}\n\t---\n\t<span color=\"red\">**무게:**</span><span color=\"red\"> </span>1 lb\n\t<span color=\"red\">**가치:**</span><span color=\"red\"> </span>1 CP\n\t---\n\t횃불은 1시간 동안 타오르며 반경 20ft에 <span color=\"yellow\">[밝은 빛](/212f7f5a1e8081239224f09b56e36bb4?pvs=25)</span>을, 그리고 추가로 반경 20ft에 <span color=\"yellow\">[약한 빛](/212f7f5a1e80816b935dfcf84e45fa93?pvs=25)</span>을 비춥니다. <span color=\"green\">[공격](/212f7f5a1e8081d09ce9fe10c371eb15?pvs=25)</span> 행동으로 횃불을 일반 근거리 무기처럼 사용할 수 있으며, 명중 시 대상에게 1점의 화염 피해를 가합니다.\n</synced_block_reference>"}